[{"username":"doctorwhocomposer","forename":"Delia","surname":"Derbyshire","adminStatus":"supermod","dp":"/User/Profile_Pictures/default.png"},{"username":"joyalrj22","forename":"Joyal","surname":"Raju","adminStatus":"mod","dp":"/User/Profile_Pictures/marcopolo.png"},{"username":"john","forename":"John","surname":"Smith","adminStatus":"none","dp":"/User/Profile_Pictures/default.png"},{"username":"doctorwhocomposer","forename":"Bob","surname":"Builder","adminStatus":"none","dp":"/User/Profile_Pictures/marcopolo.png"}]